burmese_tokenizer/__init__.py
burmese_tokenizer/cli.py
burmese_tokenizer/py.typed
burmese_tokenizer/tokenizer.py
burmese_tokenizer-0.1.3.dist-info/WHEEL
burmese_tokenizer-0.1.3.dist-info/entry_points.txt
burmese_tokenizer-0.1.3.dist-info/METADATA
burmese_tokenizer-0.1.3.dist-info/RECORD
