Metadata-Version: 2.3
Name: burmese-tokenizer
Version: 0.1.3
Summary: A simple tokenizer for Burmese text
Keywords: burmese,tokenizer,nlp,myanmar,text-processing
Author: janakhpon
Author-email: janakhpon <jnovaxer@gmail.com>
License: MIT
Classifier: Development Status :: 4 - Beta
Classifier: Intended Audience :: Developers
Classifier: Intended Audience :: Science/Research
Classifier: License :: OSI Approved :: MIT License
Classifier: Operating System :: OS Independent
Classifier: Programming Language :: Python :: 3
Classifier: Programming Language :: Python :: 3.11
Classifier: Programming Language :: Python :: 3.12
Classifier: Topic :: Scientific/Engineering :: Artificial Intelligence
Classifier: Topic :: Text Processing :: Linguistic
Classifier: Topic :: Software Development :: Libraries :: Python Modules
Requires-Dist: sentencepiece>=0.1.99
Requires-Dist: click>=8.0.0
Requires-Dist: rich>=13.0.0
Requires-Dist: twine>=6.1.0
Requires-Dist: pytest>=7.0.0 ; extra == 'dev'
Requires-Dist: pytest-cov>=4.0.0 ; extra == 'dev'
Requires-Dist: black>=23.0.0 ; extra == 'dev'
Requires-Dist: isort>=5.12.0 ; extra == 'dev'
Requires-Dist: mypy>=1.0.0 ; extra == 'dev'
Requires-Dist: ruff>=0.1.0 ; extra == 'dev'
Requires-Dist: sphinx>=7.0.0 ; extra == 'docs'
Requires-Dist: sphinx-rtd-theme>=1.3.0 ; extra == 'docs'
Requires-Python: >=3.11
Project-URL: Changelog, https://github.com/Code-Yay-Mal/burmese_tokenizer/blob/main/CHANGELOG.md
Project-URL: Documentation, https://github.com/Code-Yay-Mal/burmese_tokenizer#readme
Project-URL: Homepage, https://github.com/Code-Yay-Mal/burmese_tokenizer
Project-URL: Issues, https://github.com/Code-Yay-Mal/burmese_tokenizer/issues
Project-URL: Repository, https://github.com/Code-Yay-Mal/burmese_tokenizer
Provides-Extra: dev
Provides-Extra: docs
